video_rendering/__init__.py
video_rendering/__main__.py
video_rendering/cli.py
video_rendering/config.py
video_rendering/exceptions.py
video_rendering/py.typed
video_rendering/core/__init__.py
video_rendering/core/converter.py
video_rendering/core/ffmpeg.py
video_rendering/core/renderer.py
video_rendering/utils/__init__.py
video_rendering/utils/ffmpeg_check.py
video_rendering/utils/images.py
video_rendering-1.0.1.dist-info/METADATA
video_rendering-1.0.1.dist-info/WHEEL
video_rendering-1.0.1.dist-info/entry_points.txt
video_rendering-1.0.1.dist-info/licenses/LICENSE
video_rendering-1.0.1.dist-info/RECORD
