Metadata-Version: 2.4
Name: video-rendering
Version: 1.0.1
Summary: Convert image sequences to MP4/GIF and MP4 videos to GIF using FFmpeg
Project-URL: Homepage, https://github.com/silviobaratto/video-rendering
Project-URL: Repository, https://github.com/silviobaratto/video-rendering
Project-URL: Issues, https://github.com/silviobaratto/video-rendering/issues
Author: Silvio Baratto
License: MIT
License-File: LICENSE
Keywords: animation,ffmpeg,gif,images,mp4,rendering,video
Classifier: Development Status :: 4 - Beta
Classifier: Environment :: Console
Classifier: Intended Audience :: Developers
Classifier: License :: OSI Approved :: MIT License
Classifier: Operating System :: OS Independent
Classifier: Programming Language :: Python :: 3
Classifier: Programming Language :: Python :: 3.10
Classifier: Programming Language :: Python :: 3.11
Classifier: Programming Language :: Python :: 3.12
Classifier: Programming Language :: Python :: 3.13
Classifier: Topic :: Multimedia :: Graphics :: Graphics Conversion
Classifier: Topic :: Multimedia :: Video :: Conversion
Classifier: Typing :: Typed
Requires-Python: >=3.10
Requires-Dist: click>=8.0
Requires-Dist: natsort>=8.0
Requires-Dist: pillow>=10.0
Requires-Dist: tqdm>=4.60
Provides-Extra: dev
Requires-Dist: mypy>=1.0; extra == 'dev'
Requires-Dist: pre-commit>=3.0; extra == 'dev'
Requires-Dist: pytest-cov>=4.0; extra == 'dev'
Requires-Dist: pytest>=7.0; extra == 'dev'
Requires-Dist: ruff>=0.1.0; extra == 'dev'
